topsis/cli.py
topsis/topsis.py
topsis33-1.0.0.dist-info/LICENSE
topsis33-1.0.0.dist-info/METADATA
topsis33-1.0.0.dist-info/WHEEL
topsis33-1.0.0.dist-info/entry_points.txt
topsis33-1.0.0.dist-info/top_level.txt
topsis33-1.0.0.dist-info/RECORD
