Metadata-Version: 2.1
Name: topsis33
Version: 1.0.0
Summary: A Python package to implement Topsis
Home-page: UNKNOWN
Author: Mukul Verma
Author-email: mverma1_be17@thapar.edu
License: MIT
Platform: UNKNOWN
Classifier: License :: OSI Approved :: MIT License
Classifier: Programming Language :: Python :: 3
Classifier: Programming Language :: Python :: 3.7
Requires-Dist: numpy
Requires-Dist: pandas
